pltwal/__init__.py
pltwal/setRcParams.py
pltwal-0.0.3.dist-info/LICENSE
pltwal-0.0.3.dist-info/METADATA
pltwal-0.0.3.dist-info/WHEEL
pltwal-0.0.3.dist-info/top_level.txt
pltwal-0.0.3.dist-info/RECORD
