Metadata-Version: 2.1
Name: pltwal
Version: 0.0.3
Summary: Uses pywal colorscheme for pyplot rcParams
Home-page: 
Author: Sebastian Wohlrab
Author-email: Sebastian Wohlrab <sebastian.wohlrab@wohlrab.de>
License: GNU GENERAL PUBLIC LICENSE
Project-URL: Homepage, https://github.com/snwohlrab/pltwal
Project-URL: Issues, https://github.com/snwohlrab/pltwal/issues
Classifier: Programming Language :: Python :: 3
Classifier: Operating System :: OS Independent
Requires-Python: >=3.8
License-File: LICENSE
